poropto/__init__.py
poropto/portfolio_optimization.py
poropto/preliminaries.py
poropto/return_evaluation.py
poropto/sustainability_evaluation.py
poropto-0.1.0.dist-info/licenses/LICENSE.txt
poropto-0.1.0.dist-info/METADATA
poropto-0.1.0.dist-info/WHEEL
poropto-0.1.0.dist-info/entry_points.txt
poropto-0.1.0.dist-info/top_level.txt
poropto-0.1.0.dist-info/RECORD
