Metadata-Version: 2.4
Name: poropto
Version: 0.1.0
Summary: Sustainable multi-objective portfolio optimization with intuitionistic fuzzy linear programming (IIFLP).
Author-email: Nazanin Ghaemizadeh <ghaemi.nazanin@ie.sharif.edu>
License-Expression: MIT
Project-URL: Homepage, https://github.com/nazanin-ghaemizadeh/POROPTO-Portfolio-Optimization-Package
Project-URL: Issues, https://github.com/nazanin-ghaemizadeh/POROPTO-Portfolio-Optimization-Package/issues
Keywords: portfolio optimization,fuzzy,intuitionistic fuzzy,pyomo,ESG,entropy
Classifier: Programming Language :: Python :: 3
Classifier: Programming Language :: Python :: 3.8
Classifier: Programming Language :: Python :: 3.9
Classifier: Programming Language :: Python :: 3.10
Classifier: Programming Language :: Python :: 3.11
Classifier: Operating System :: OS Independent
Classifier: Intended Audience :: Science/Research
Classifier: Topic :: Scientific/Engineering :: Mathematics
Requires-Python: >=3.8
License-File: LICENSE.txt
Requires-Dist: numpy>=1.21
Requires-Dist: pandas>=1.3
Requires-Dist: scipy>=1.7
Requires-Dist: pyomo>=6.4
Requires-Dist: matplotlib>=3.4
Dynamic: license-file
